aiohttp_basicauth_middleware/__init__.py
aiohttp_basicauth_middleware/strategy.py
aiohttp_basicauth_middleware-1.1.0.dist-info/LICENSE
aiohttp_basicauth_middleware-1.1.0.dist-info/METADATA
aiohttp_basicauth_middleware-1.1.0.dist-info/WHEEL
aiohttp_basicauth_middleware-1.1.0.dist-info/top_level.txt
aiohttp_basicauth_middleware-1.1.0.dist-info/RECORD
