Metadata-Version: 2.1
Name: aiohttp-basicauth-middleware
Version: 1.1.0
Summary: An incredibly simple HTTP basic auth implementation for Aiohttp.
Home-page: https://github.com/bugov/aiohttp-basicauth-middleware
Author: Georgy Bazhukov
Author-email: georgy.bazhukov@gmail.com
License: BSD
Keywords: aiohttp security basicauth http middleware
Platform: UNKNOWN
Classifier: License :: Public Domain
Classifier: Programming Language :: Python
Classifier: Programming Language :: Python :: 3
Classifier: Programming Language :: Python :: 3.5
Classifier: Programming Language :: Python :: 3.6
Requires: http_basic_auth
Requires: aiohttp
Requires-Dist: http-basic-auth
Requires-Dist: aiohttp
